{
  "@context": {
    "schema": "http://schema.org/",
    "dc": "http://purl.org/dc/elements/1.1/",
    "dct": "http://dublincore.org/terms/",
    "rdf": "http://www.w3.org/1999/02/22-rdf-syntax-ns#",
    "rdfs": "http://www.w3.org/2000/01/rdf-schema#",
    "ctdl": "[CTI Namespace Not Determined Yet]"
  },
  "@type": "ctdl:Organization",
  "ctdl:agentCategory": 0,
  "ctdl:address": {
    "@type": "Nope",
    "other-thing": "bla"
  },
  "ctdl:email": "invalid@mail",
  "ctdl:sameAs": [
    "http://www.aama-ntl.org/images/web-design-images/aama-header-logo.gif?sfvrsn=4",
    "http://www.aama-ntl.org/contact"
  ],
 "ctdl:url": "not-url"
}
